<annotation>
	<folder>captcha</folder>
	<filename>718.png</filename>
	<path>C:\Users\T.Buzheyev\Downloads\help_label\captcha\718.png</path>
	<source>
		<database>Unknown</database>
	</source>
	<size>
		<width>160</width>
		<height>60</height>
		<depth>1</depth>
	</size>
	<segmented>0</segmented>
	<object>
		<name>Л</name>
		<pose>Unspecified</pose>
		<truncated>0</truncated>
		<difficult>0</difficult>
		<bndbox>
			<xmin>41</xmin>
			<ymin>24</ymin>
			<xmax>61</xmax>
			<ymax>47</ymax>
		</bndbox>
	</object>
	<object>
		<name>П</name>
		<pose>Unspecified</pose>
		<truncated>0</truncated>
		<difficult>0</difficult>
		<bndbox>
			<xmin>60</xmin>
			<ymin>23</ymin>
			<xmax>76</xmax>
			<ymax>43</ymax>
		</bndbox>
	</object>
	<object>
		<name>Ф</name>
		<pose>Unspecified</pose>
		<truncated>0</truncated>
		<difficult>0</difficult>
		<bndbox>
			<xmin>79</xmin>
			<ymin>19</ymin>
			<xmax>91</xmax>
			<ymax>43</ymax>
		</bndbox>
	</object>
	<object>
		<name>З</name>
		<pose>Unspecified</pose>
		<truncated>0</truncated>
		<difficult>0</difficult>
		<bndbox>
			<xmin>93</xmin>
			<ymin>20</ymin>
			<xmax>102</xmax>
			<ymax>41</ymax>
		</bndbox>
	</object>
	<object>
		<name>Х</name>
		<pose>Unspecified</pose>
		<truncated>0</truncated>
		<difficult>0</difficult>
		<bndbox>
			<xmin>102</xmin>
			<ymin>17</ymin>
			<xmax>118</xmax>
			<ymax>38</ymax>
		</bndbox>
	</object>
</annotation>
