<annotation>
	<folder>clean_unnamed</folder>
	<filename>140.png</filename>
	<path>C:\Users\T.Buzheyev\Downloads\help_label\captcha 2\clean_unnamed\140.png</path>
	<source>
		<database>Unknown</database>
	</source>
	<size>
		<width>160</width>
		<height>60</height>
		<depth>3</depth>
	</size>
	<segmented>0</segmented>
	<object>
		<name>З</name>
		<pose>Unspecified</pose>
		<truncated>0</truncated>
		<difficult>0</difficult>
		<bndbox>
			<xmin>29</xmin>
			<ymin>25</ymin>
			<xmax>50</xmax>
			<ymax>43</ymax>
		</bndbox>
	</object>
	<object>
		<name>Я</name>
		<pose>Unspecified</pose>
		<truncated>0</truncated>
		<difficult>0</difficult>
		<bndbox>
			<xmin>50</xmin>
			<ymin>24</ymin>
			<xmax>67</xmax>
			<ymax>43</ymax>
		</bndbox>
	</object>
	<object>
		<name>Ф</name>
		<pose>Unspecified</pose>
		<truncated>0</truncated>
		<difficult>0</difficult>
		<bndbox>
			<xmin>67</xmin>
			<ymin>22</ymin>
			<xmax>84</xmax>
			<ymax>37</ymax>
		</bndbox>
	</object>
	<object>
		<name>І</name>
		<pose>Unspecified</pose>
		<truncated>0</truncated>
		<difficult>0</difficult>
		<bndbox>
			<xmin>85</xmin>
			<ymin>22</ymin>
			<xmax>93</xmax>
			<ymax>35</ymax>
		</bndbox>
	</object>
	<object>
		<name>С</name>
		<pose>Unspecified</pose>
		<truncated>0</truncated>
		<difficult>0</difficult>
		<bndbox>
			<xmin>96</xmin>
			<ymin>21</ymin>
			<xmax>114</xmax>
			<ymax>35</ymax>
		</bndbox>
	</object>
	<object>
		<name>К</name>
		<pose>Unspecified</pose>
		<truncated>0</truncated>
		<difficult>0</difficult>
		<bndbox>
			<xmin>113</xmin>
			<ymin>21</ymin>
			<xmax>131</xmax>
			<ymax>39</ymax>
		</bndbox>
	</object>
</annotation>
